topaisdk/__init__.py
topaisdk/metrics.py
topaisdk/modelservice.py
topaisdk-0.2.4.dist-info/METADATA
topaisdk-0.2.4.dist-info/WHEEL
topaisdk-0.2.4.dist-info/top_level.txt
topaisdk-0.2.4.dist-info/RECORD
