Metadata-Version: 2.1
Name: topaisdk
Version: 0.2.4
Summary: topai python sdk
Home-page: http://github.com/topailab
Author: error.ding
Author-email: error.ding@uptech.ai
Classifier: Programming Language :: Python :: 3.10
Classifier: License :: OSI Approved :: MIT License
Classifier: Operating System :: OS Independent
Requires-Python: >=3.10
Requires-Dist: ray==2.34.0
